{
  "type": "FeatureCollection",
  "name": "maetore_2026-07-05_eveningIn_route",
  "features": [
    {
      "type": "Feature",
      "geometry": {
        "type": "Point",
        "coordinates": [
          29.3993861,
          -23.8799718
        ]
      },
      "properties": {
        "sequence": 1,
        "type": "pickup",
        "name": "Sensory Vukeya pickup",
        "passenger_count": 1,
        "passengers": "Sensory Vukeya",
        "note": "Ext 76 pickup"
      }
    },
    {
      "type": "Feature",
      "geometry": {
        "type": "Point",
        "coordinates": [
          29.4210221,
          -23.8860013
        ]
      },
      "properties": {
        "sequence": 2,
        "type": "pickup",
        "name": "Frans Mokgehle pickup",
        "passenger_count": 1,
        "passengers": "Frans Mokgehle",
        "note": "Ext 78 pickup"
      }
    },
    {
      "type": "Feature",
      "geometry": {
        "type": "Point",
        "coordinates": [
          29.5160153,
          -23.8978861
        ]
      },
      "properties": {
        "sequence": 3,
        "type": "dropoff",
        "name": "Sasol R71",
        "passenger_count": 2,
        "passengers": "Sensory Vukeya, Frans Mokgehle",
        "note": "Inbound dropoff ordered by distance to R71"
      }
    }
  ]
}
