{
  "type": "FeatureCollection",
  "name": "maetore_2026-07-15_morningOut_route",
  "features": [
    {
      "type": "Feature",
      "geometry": {
        "type": "Point",
        "coordinates": [
          29.5160153,
          -23.8978861
        ]
      },
      "properties": {
        "sequence": 1,
        "type": "pickup",
        "name": "Sasol R71",
        "passenger_count": 1,
        "passengers": "Sensory Vukeya",
        "note": "Outbound pickup ordered by distance from R71"
      }
    },
    {
      "type": "Feature",
      "geometry": {
        "type": "Point",
        "coordinates": [
          29.4754902,
          -23.9133595
        ]
      },
      "properties": {
        "sequence": 2,
        "type": "pickup",
        "name": "MBT Florapark",
        "passenger_count": 1,
        "passengers": "Linah Molelemane",
        "note": "Outbound pickup ordered by distance from R71"
      }
    },
    {
      "type": "Feature",
      "geometry": {
        "type": "Point",
        "coordinates": [
          29.4068004,
          -23.887007
        ]
      },
      "properties": {
        "sequence": 3,
        "type": "dropoff",
        "name": "Linah Molelemane dropoff",
        "passenger_count": 1,
        "passengers": "Linah Molelemane",
        "note": "Ext 71 dropoff"
      }
    },
    {
      "type": "Feature",
      "geometry": {
        "type": "Point",
        "coordinates": [
          29.3993861,
          -23.8799718
        ]
      },
      "properties": {
        "sequence": 4,
        "type": "dropoff",
        "name": "Sensory Vukeya dropoff",
        "passenger_count": 1,
        "passengers": "Sensory Vukeya",
        "note": "Ext 76 dropoff"
      }
    }
  ]
}
