{
  "type": "FeatureCollection",
  "name": "maetore_2026-07-19_eveningOut_route",
  "features": [
    {
      "type": "Feature",
      "geometry": {
        "type": "Point",
        "coordinates": [
          29.5160153,
          -23.8978861
        ]
      },
      "properties": {
        "sequence": 1,
        "type": "pickup",
        "name": "Sasol R71",
        "passenger_count": 1,
        "passengers": "Sensory Vukeya",
        "note": "Outbound pickup ordered by distance from R71"
      }
    },
    {
      "type": "Feature",
      "geometry": {
        "type": "Point",
        "coordinates": [
          29.4593845,
          -23.9052611
        ]
      },
      "properties": {
        "sequence": 2,
        "type": "pickup",
        "name": "Sasol Jorrisen",
        "passenger_count": 1,
        "passengers": "Happy Choeu",
        "note": "Outbound pickup ordered by distance from R71"
      }
    },
    {
      "type": "Feature",
      "geometry": {
        "type": "Point",
        "coordinates": [
          29.3993861,
          -23.8799718
        ]
      },
      "properties": {
        "sequence": 3,
        "type": "dropoff",
        "name": "Sensory Vukeya dropoff",
        "passenger_count": 1,
        "passengers": "Sensory Vukeya",
        "note": "Ext 76 dropoff"
      }
    },
    {
      "type": "Feature",
      "geometry": {
        "type": "Point",
        "coordinates": [
          29.3505369,
          -23.8195461
        ]
      },
      "properties": {
        "sequence": 4,
        "type": "dropoff",
        "name": "Happy Choeu dropoff",
        "passenger_count": 1,
        "passengers": "Happy Choeu",
        "note": "Spook Park dropoff"
      }
    }
  ]
}
