{
  "type": "FeatureCollection",
  "name": "maetore_2026-07-12_eveningIn_route",
  "features": [
    {
      "type": "Feature",
      "geometry": {
        "type": "Point",
        "coordinates": [
          29.3505369,
          -23.8195461
        ]
      },
      "properties": {
        "sequence": 1,
        "type": "pickup",
        "name": "Happy Choeu pickup",
        "passenger_count": 1,
        "passengers": "Happy Choeu",
        "note": "Spook Park pickup"
      }
    },
    {
      "type": "Feature",
      "geometry": {
        "type": "Point",
        "coordinates": [
          29.3507395,
          -23.8196517
        ]
      },
      "properties": {
        "sequence": 2,
        "type": "pickup",
        "name": "Lesiba Choeu pickup",
        "passenger_count": 1,
        "passengers": "Lesiba Choeu",
        "note": "Spook Park pickup"
      }
    },
    {
      "type": "Feature",
      "geometry": {
        "type": "Point",
        "coordinates": [
          29.4593845,
          -23.9052611
        ]
      },
      "properties": {
        "sequence": 3,
        "type": "dropoff",
        "name": "Sasol Jorrisen",
        "passenger_count": 1,
        "passengers": "Happy Choeu",
        "note": "Inbound dropoff ordered by distance to R71"
      }
    },
    {
      "type": "Feature",
      "geometry": {
        "type": "Point",
        "coordinates": [
          29.5160153,
          -23.8978861
        ]
      },
      "properties": {
        "sequence": 4,
        "type": "dropoff",
        "name": "Sasol R71",
        "passenger_count": 1,
        "passengers": "Lesiba Choeu",
        "note": "Inbound dropoff ordered by distance to R71"
      }
    }
  ]
}
