{
  "type": "FeatureCollection",
  "name": "maetore_2026-07-22_eveningIn_route",
  "features": [
    {
      "type": "Feature",
      "geometry": {
        "type": "Point",
        "coordinates": [
          29.3507395,
          -23.8196517
        ]
      },
      "properties": {
        "sequence": 1,
        "type": "pickup",
        "name": "Lesiba Choeu pickup",
        "passenger_count": 1,
        "passengers": "Lesiba Choeu",
        "note": "Spook Park pickup"
      }
    },
    {
      "type": "Feature",
      "geometry": {
        "type": "Point",
        "coordinates": [
          29.3969942,
          -23.8827173
        ]
      },
      "properties": {
        "sequence": 2,
        "type": "pickup",
        "name": "Portia Munyai pickup",
        "passenger_count": 1,
        "passengers": "Portia Munyai",
        "note": "Ext 76 pickup"
      }
    },
    {
      "type": "Feature",
      "geometry": {
        "type": "Point",
        "coordinates": [
          29.5160153,
          -23.8978861
        ]
      },
      "properties": {
        "sequence": 3,
        "type": "dropoff",
        "name": "Sasol R71",
        "passenger_count": 2,
        "passengers": "Lesiba Choeu, Portia Munyai",
        "note": "Inbound dropoff ordered by distance to R71"
      }
    }
  ]
}
