{
  "type": "FeatureCollection",
  "name": "maetore_2026-07-17_eveningOut_route",
  "features": [
    {
      "type": "Feature",
      "geometry": {
        "type": "Point",
        "coordinates": [
          29.4593845,
          -23.9052611
        ]
      },
      "properties": {
        "sequence": 1,
        "type": "pickup",
        "name": "Sasol Jorrisen",
        "passenger_count": 1,
        "passengers": "Happy Choeu",
        "note": "Outbound pickup ordered by distance from R71"
      }
    },
    {
      "type": "Feature",
      "geometry": {
        "type": "Point",
        "coordinates": [
          29.3505369,
          -23.8195461
        ]
      },
      "properties": {
        "sequence": 2,
        "type": "dropoff",
        "name": "Happy Choeu dropoff",
        "passenger_count": 1,
        "passengers": "Happy Choeu",
        "note": "Spook Park dropoff"
      }
    }
  ]
}
